NiukeDaShujuKaifaGangQiuzhiJingyanFenxiang20212022Fix1/README.md
NiukeDaShujuKaifaGangQiuzhiJingyanFenxiang20212022Fix1/__init__.py
NiukeDaShujuKaifaGangQiuzhiJingyanFenxiang20212022Fix1/__main__.py
NiukeDaShujuKaifaGangQiuzhiJingyanFenxiang20212022Fix1/file.epub
NiukeDaShujuKaifaGangQiuzhiJingyanFenxiang20212022Fix1/index.html
NiukeDaShujuKaifaGangQiuzhiJingyanFenxiang20212022Fix1/css/__init__.py
NiukeDaShujuKaifaGangQiuzhiJingyanFenxiang20212022Fix1/css/annotations.css
NiukeDaShujuKaifaGangQiuzhiJingyanFenxiang20212022Fix1/css/main.css
NiukeDaShujuKaifaGangQiuzhiJingyanFenxiang20212022Fix1/css/normalize.css
NiukeDaShujuKaifaGangQiuzhiJingyanFenxiang20212022Fix1/css/popup.css
NiukeDaShujuKaifaGangQiuzhiJingyanFenxiang20212022Fix1/font/__init__.py
NiukeDaShujuKaifaGangQiuzhiJingyanFenxiang20212022Fix1/font/fontello.eot
NiukeDaShujuKaifaGangQiuzhiJingyanFenxiang20212022Fix1/font/fontello.svg
NiukeDaShujuKaifaGangQiuzhiJingyanFenxiang20212022Fix1/font/fontello.ttf
NiukeDaShujuKaifaGangQiuzhiJingyanFenxiang20212022Fix1/font/fontello.woff
NiukeDaShujuKaifaGangQiuzhiJingyanFenxiang20212022Fix1/img/__init__.py
NiukeDaShujuKaifaGangQiuzhiJingyanFenxiang20212022Fix1/img/annotator-glyph-sprite.png
NiukeDaShujuKaifaGangQiuzhiJingyanFenxiang20212022Fix1/img/annotator-icon-sprite.png
NiukeDaShujuKaifaGangQiuzhiJingyanFenxiang20212022Fix1/img/apple-touch-icon.png
NiukeDaShujuKaifaGangQiuzhiJingyanFenxiang20212022Fix1/img/cancelfullscreen.png
NiukeDaShujuKaifaGangQiuzhiJingyanFenxiang20212022Fix1/img/close.png
NiukeDaShujuKaifaGangQiuzhiJingyanFenxiang20212022Fix1/img/fullscreen.png
NiukeDaShujuKaifaGangQiuzhiJingyanFenxiang20212022Fix1/img/loader.gif
NiukeDaShujuKaifaGangQiuzhiJingyanFenxiang20212022Fix1/img/menu-icon.png
NiukeDaShujuKaifaGangQiuzhiJingyanFenxiang20212022Fix1/img/save.png
NiukeDaShujuKaifaGangQiuzhiJingyanFenxiang20212022Fix1/img/saved.png
NiukeDaShujuKaifaGangQiuzhiJingyanFenxiang20212022Fix1/img/settings-s.png
niuke_da_shuju_kaifa_gang_qiuzhi_jingyan_fenxiang_2021_2022_fix1-2025.3.25.1.dist-info/METADATA
niuke_da_shuju_kaifa_gang_qiuzhi_jingyan_fenxiang_2021_2022_fix1-2025.3.25.1.dist-info/WHEEL
niuke_da_shuju_kaifa_gang_qiuzhi_jingyan_fenxiang_2021_2022_fix1-2025.3.25.1.dist-info/entry_points.txt
niuke_da_shuju_kaifa_gang_qiuzhi_jingyan_fenxiang_2021_2022_fix1-2025.3.25.1.dist-info/top_level.txt
niuke_da_shuju_kaifa_gang_qiuzhi_jingyan_fenxiang_2021_2022_fix1-2025.3.25.1.dist-info/RECORD
